{
  "tasks": [
    {
      "id": "CP-cplq76ig4",
      "title": "Pr-3",
      "priority": "medium",
      "status": "done",
      "desc": "kjnkdfjnk kkjnfnkv"
    },
    {
      "id": "CP-eb51uejsz",
      "title": "P-1",
      "priority": "low",
      "status": "in-progress",
      "desc": "This Project is about the development of te Advedutech"
    },
    {
      "id": "CP-8vk5s3l0a",
      "title": "VirtualLabs",
      "priority": "high",
      "status": "todo",
      "desc": "The ERP Platform for CorrectSteps"
    },
    {
      "id": "CP-ve5sskn6c",
      "title": "Pr-4",
      "priority": "low",
      "status": "in-progress",
      "desc": "Yare yare !!"
    }
  ]
}